prelims_cli/__init__.py
prelims_cli/cli.py
prelims_cli/config/__init__.py
prelims_cli/config/config.yaml
prelims_cli/ja/__init__.py
prelims_cli/ja/tokenizer.py
prelims_cli-0.0.4.dist-info/entry_points.txt
prelims_cli-0.0.4.dist-info/LICENSE
prelims_cli-0.0.4.dist-info/WHEEL
prelims_cli-0.0.4.dist-info/METADATA
prelims_cli-0.0.4.dist-info/RECORD
