Metadata-Version: 2.1
Name: prelims-cli
Version: 0.0.4
Summary: prelims CLI - Front matter post-processor CLI
Home-page: https://github.com/chezou/prelims-cli
License: MIT
Author: Aki Ariga
Author-email: chezou@gmail.com
Maintainer: Aki Ariga
Maintainer-email: chezou@gmail.com
Requires-Python: >=3.10,<3.11
Classifier: License :: OSI Approved :: MIT License
Classifier: Programming Language :: Python :: 3
Classifier: Programming Language :: Python :: 3.10
Provides-Extra: ja
Requires-Dist: SudachiDict-full (>=20211220,<20211221); extra == "ja"
Requires-Dist: SudachiPy (>=0.6.2,<0.7.0); extra == "ja"
Requires-Dist: click (>=8.0.3,<9.0.0)
Requires-Dist: numpy (>=1.22.1,<2.0.0)
Requires-Dist: omegaconf (>=2.1.1,<3.0.0)
Requires-Dist: prelims (>=0.0.6,<0.0.7)
Requires-Dist: scipy (>=1.7.3,<2.0.0)
Requires-Dist: taskipy (>=1.9.0,<2.0.0)
Project-URL: Repository, https://github.com/chezou/prelims-cli
